[
        {
            "position": [
                51.51268,
                -0.12051
            ],
            "title": "Theatre Royal Drury Lane",
            "imageUrl": "https://cdn.thestage.co.uk/wp-content/uploads/2017/09/18164826/Theatre-Royal_Auditorium-from-the-Royal-Box_CopyrightPeterDazeley_credit-photographer-Peter-Dazeley-700x455.jpg",
            "description": "The Theatre Royal, Drury Lane, commonly known as Drury Lane, is a West End theatre and Grade I listed building in Covent Garden, London, England. The building faces Catherine Street and backs onto Drury Lane.",
            "city": "london",
            "link": "https://wego.here.com/united-kingdom/london/theatre-music-culture/theatre-royal-drury-lane--826gcpvj-571dc32a030f4dedbc9db406648fcea5?map=51.51268,-0.12051,15,normal&x=ep"
        },
        {
            "position": [
                51.50366,
                -0.11925
            ],
            "title": "London Eye",
            "imageUrl": "https://cdn.londonandpartners.com/asset/20adda9d08e8480c6dbbfcf30fbcabdb.jpg",
            "description": "The London Eye, known for sponsorship reasons as the Coca-Cola London Eye, is a giant Ferris wheel on the South Bank of the River Thames in London. The structure is 135 metres tall and the wheel has a diameter of 120 metres.",
            "city": "london",
            "link": "https://wego.here.com/united-kingdom/london/sights-museums/coca-cola-london-eye--826gcpuv-8a14d169f6e54810a56a01704d0461b5?map=51.50366,-0.11925,15,normal&x=ep"
        },
        {
            "position": [
                51.50853,
                -0.12794
            ],
            "title": "National Gallery",
            "imageUrl": "https://cdn.londonandpartners.com/asset/national-gallery-the-national-gallery-trafalgar-square-69bf160c36657f11199b87c236aec7f7.jpg",
            "description": "The National Gallery is an art museum in Trafalgar Square in the City of Westminster, in Central London. Founded in 1824, it houses a collection of over 2,300 paintings dating from the mid-13th century to 1900.",
            "city": "london",
            "link": "https://wego.here.com/united-kingdom/london/sights-museums/national-gallery--826gcpvj-46744b9ff4b94b76abe402c8adf69d31?map=51.50853,-0.12794,15,normal&x=ep"
        },
        {
            "position": [
                51.51176,
                -0.11791
            ],
            "title": "Somerset House",
            "imageUrl": "https://www.somersethouse.org.uk/sites/default/files/styles/header_image/public/HEADER%202_The%20Edmond%20J.%20Safra%20Fountain%20Court_IMG_0435.jpg?itok=HCKiwBFi",
            "description": "Somerset House is a large Neoclassical building situated on the south side of the Strand in central London, overlooking the River Thames, just east of Waterloo Bridge. ",
            "city": "london",
            "link": "https://wego.here.com/united-kingdom/london/sights-museums/somerset-house--826gcpvj-9b9cb9fef9e34ab4beae220a9b454c7a?map=51.51176,-0.11791,15,normal&x=ep"
        },
        {
            "position": [
                51.5187,
                -0.12504
            ],
            "title": "British museum",
            "imageUrl": "https://www.artfund.org/assets/what-to-see/museums-and-galleries/a-c/british-museum/british-museum-exterior_1.jpg",
            "description": "The British Museum, located in the Bloomsbury area of London, United Kingdom, is a public institution dedicated to human history, art and culture.",
            "city": "london",
            "link": "https://wego.here.com/united-kingdom/london/museum/british-museum--826gcpvj-99722f1088e640048ff5f334e6cc2a9a?map=51.5187,-0.12504,15,normal&x=ep"
        },
        {
            "position": [
                51.500382,
                -0.1239
            ],
            "title": "Big Ben",
            "imageUrl": "https://media-cdn.tripadvisor.com/media/photo-s/08/dd/25/05/big-ben.jpg",
            "description": "Big Ben is the nickname for the Great Bell of the clock at the north end of the Palace of Westminster in London and is usually extended to refer to both the clock and the clock tower.",
            "city": "london",
            "link": "https://wego.here.com/united-kingdom/london/landmark-attraction/big-ben--826gcpu7-879412259a2c484a99f8de9da21f44c1?map=51.500382,-0.1239,15,normal&x=ep"
        },
        {
            "position": [
                51.50739,
                -0.10127
            ],
            "title": "Tate Modern",
            "imageUrl": "https://cdn.londonandpartners.com/asset/08d213af8554399bb00a96bd0be145b5.jpg",
            "description": "Tate Modern is a modern art gallery located in London. It is Britain's national gallery of international modern art and forms part of the Tate group.",
            "city": "london",
            "link": "https://wego.here.com/united-kingdom/london/museum/tate-modern--826gcpvj-1800ed7a2ebe4105a8e2827263e38b83?map=51.50739,-0.10127,15,normal&x=ep"
        },
        {
            "position": [
                51.50316,
                -0.12678
            ],
            "title": "10 Downing Street",
            "imageUrl": "https://i.pinimg.com/originals/70/5b/8e/705b8e1a35fff015c246e665ddc48e04.jpg",
            "description": "10 Downing Street, colloquially known in the United Kingdom as Number 10, is the headquarters of the Government of the United Kingdom and the official residence and office of the First Lord of the Treasury, a post which, for much of the 18th and 19th centuries and invariably since 1905, has been held by the Prime Minister.",
            "city": "london",
            "link": "https://wego.here.com/united-kingdom/london/sights-museums/10-downing-street--826gcpuv-a6b51b633e394814b9345948283badeb?map=51.50316,-0.12678,15,normal&x=ep"
        },
        {
            "position": [
                51.51344,
                -0.09974
            ],
            "title": "St Paul's Cathedral",
            "imageUrl": "https://d1wgio6yfhqlw1.cloudfront.net/sysimages/product/resized6/St_Pauls_2542_29054.jpg",
            "description": "St Paul's Cathedral, London, is an Anglican cathedral, the seat of the Bishop of London and the mother church of the Diocese of London. It sits on Ludgate Hill at the highest point of the City of London and is a Grade I listed building.",
            "city": "london",
            "link": "https://wego.here.com/united-kingdom/london/religious-place/st-pauls-cathedral--826gcpvj-bd309a11e8d3457aa6c68d0de084156e?map=51.51344,-0.09974,15,normal&x=ep"
        },
        {
            "position": [
                51.49954,
                -0.12864
            ],
            "title": "Westminster Abbey",
            "imageUrl": "https://cdn.londonandpartners.com/asset/westminster-abbey-westminster-abbey-e7fd5ab22fe5e9dc0fb2a4b7f3e593f3.jpg",
            "description": "The Westminster Abbey Museum was located in the 11th-century vaulted undercroft beneath the former monks' dormitory in Westminster Abbey, London, England.",
            "city": "london",
            "link": "https://wego.here.com/united-kingdom/london/landmark-attraction/westminster-abbey--826gcpuv-44252d6e4aff47de906a7e328a88a598?map=51.49954,-0.12864,15,normal&x=ep"
        },
        {
            "position": [
                51.51217,
                -0.12198
            ],
            "title": "London Transport Museum",
            "imageUrl": "http://www.worldwalla.co.uk/wp-content/uploads/2017/08/london-transport.jpg",
            "description": "The London Transport Museum, or LT Museum based in Covent Garden, London, seeks to conserve and explain the transport heritage of Britain's capital city.",
            "city": "london",
            "link": "https://wego.here.com/united-kingdom/london/sights-museums/london-transport-museum--826gcpvj-2fc39bf875264d119670ad612e9f7a67?map=51.51217,-0.12198,15,normal&x=ep"
        },
        {
            "position": [
                51.51103,
                -0.12707
            ],
            "title": "Noel Coward Theatre",
            "imageUrl": "https://www.delfontmackintosh.co.uk/images/theatres/noel-coward-theatre/noel-coward-theatre-photograph-51.jpg",
            "description": "The Noël Coward Theatre, formerly known as the Albery Theatre, is a West End theatre on St. Martin's Lane in the City of Westminster, London.",
            "city": "london",
            "link": "https://wego.here.com/united-kingdom/london/theatre-music-culture/noel-coward-theatre--826gcpvj-c1cccca1daa94149b6bc18a0033111eb?map=51.51103,-0.12707,15,normal&x=ep"
        },
        {
            "position": [
                51.51027,
                -0.13225
            ],
            "title": "Prince of Wales Theatre",
            "imageUrl": "http://www.theatreticketsdirect.co.uk/Content/Media/4-232-Prince-seating.jpg",
            "description": "The Prince of Wales Theatre is a West End theatre in Coventry Street, near Leicester Square in London. It was established in 1884 and rebuilt in 1937, and extensively refurbished in 2004 by Sir Cameron Mackintosh, its current owner.",
            "city": "london",
            "link": "https://wego.here.com/united-kingdom/london/theatre-music-culture/prince-of-wales-theatre--826gcpvh-20bbbf1d92844ddeab017b5ad13fe2c2?map=51.51027,-0.13225,15,normal&x=ep"
        },
        {
            "position": [
                51.510434,
                -0.122755
            ],
            "title": "Kinky Boots at Adelphi Theatre",
            "imageUrl": "https://media.timeout.com/images/102862037/630/472/image.jpg",
            "description": "Kinky Boots is a Broadway musical with music and lyrics by Cyndi Lauper and a book by Harvey Fierstein.",
            "city": "london",
            "link": "https://wego.here.com/united-kingdom/london/theatre-music-culture/kinky-boots-at-adelphi-theatre--826aabd1-30b03f85565e0492e21b993ae83bc4b2?map=51.510434,-0.122755,15,normal&x=ep"
        },
        {
            "position": [
                51.50226,
                -0.12971
            ],
            "title": "Churchill War Rooms",
            "imageUrl": "https://www.iwm.org.uk/sites/default/files/styles/feature_hero_desktop_1x/public/2017-11/iwm_churchill.jpg?itok=Si9OUfav",
            "description": "The Churchill War Rooms is a museum in London and one of the five branches of the Imperial War Museum.",
            "city": "london",
            "link": "https://wego.here.com/united-kingdom/london/sights-museums/churchill-war-rooms--826gcpuv-470b37f113db4237be915ab18a5df181?map=51.50226,-0.12971,15,normal&x=ep"
        },
        {
            "position": [
                51.49674,
                -0.10856
            ],
            "title": "Imperial War Museum",
            "imageUrl": "https://secure.i.telegraph.co.uk/multimedia/archive/02150/The-Imperial-War-M_2150703b.jpg",
            "description": "The Imperial War Museum in London and its ground-breaking galleries tell the stories of people whose lives have been forever impacted by conflict, from the First World War to the present day.",
            "city": "london",
            "link": "https://wego.here.com/united-kingdom/london/museum/imperial-war-museum--826gcpuv-1ad999bc43034007931e8363bb0d7a35?map=51.49674,-0.10856,15,normal&x=ep"
        },
        {
            "position": [
                51.501326,
                -0.141873
            ],
            "title": "Buckingham Palace",
            "imageUrl": "https://cdn.londonandpartners.com/visit/london-organisations/buckingham-palace/100223-640x360-buckingham-palace-dusk-640.jpg",
            "description": "Buckingham Palace is the London residence and administrative headquarters of the monarch of the United Kingdom. Located in the City of Westminster, the palace is often at the centre of state occasions and royal hospitality.",
            "city": "london",
            "link": "https://wego.here.com/united-kingdom/london/landmark-attraction/buckingham-palace--826gcpuu-1fd5cbe8c1a74090ace6c5713400325a?map=51.501326,-0.141873,15,normal&x=ep"
        },
        {
            "position": [
                51.50547,
                -0.11582
            ],
            "title": "Southbank Centre",
            "imageUrl": "https://cdn.londonandpartners.com/asset/952589daf6581a51ccbafe5e94a78b97.jpg",
            "description": "Southbank Centre is a world-famous, multi-venue arts centre in London, with a dynamic year-round festivals programme and an inclusive ethos.",
            "city": "london",
            "link": "https://wego.here.com/united-kingdom/london/museum/southbank-centre--826gcpvj-734b50a601c142919903064bb17ce39f?map=51.50547,-0.11582,15,normal&x=ep"
        },
        {
            "position": [
                51.5006,
                -0.1261
            ],
            "title": "Houses of Parliament",
            "imageUrl": "https://upload.wikimedia.org/wikipedia/commons/9/97/Palace_of_Westminster%2C_London_-_Feb_2007.jpg",
            "description": "The Palace of Westminster is the meeting place of the House of Commons and the House of Lords, the two houses of the Parliament of the United Kingdom. ",
            "city": "london",
            "link": "https://wego.here.com/united-kingdom/london/landmark-attraction/houses-of-parliament--826gcpuv-068876fa3774459babad001a8b11ee6a?map=51.5006,-0.1261,15,normal&x=ep"
        },
        {
            "position": [
                51.51333,
                -0.12217
            ],
            "title": "Royal Opera House",
            "imageUrl": "https://static.standard.co.uk/s3fs-public/thumbnails/image/2016/05/25/11/royal-opera-house.jpg?w968h681",
            "description": "The Royal Opera House is an opera house and major performing arts venue in Covent Garden, central London.",
            "city": "london",
            "link": "https://wego.here.com/united-kingdom/london/theatre-music-culture/royal-opera-house--826gcpvj-58cda992b1314380b4835f2fe095f6c1?map=51.51333,-0.12217,15,normal&x=ep"
        },
        {
            "position": [
                51.517671,
                -0.096173
            ],
            "title": "Museum of London",
            "imageUrl": "https://www.artfund.org/assets/what-to-see/museums-and-galleries/k-m/museum-of-london/museum-of-london-exterior.jpg",
            "description": "The Museum of London documents the history of the English capital city from prehistoric to modern times.",
            "city": "london",
            "link": "https://wego.here.com/united-kingdom/london/museum/museum-of-london--826gcpvj-ef6441362363409f9e5c0d2cc80d10cf?map=51.517671,-0.096173,15,normal&x=ep"
        },
        {
            "position": [
                51.504925,
                -0.090344
            ],
            "title": "Borough Market",
            "imageUrl": "https://thenudge.com/wp-content/uploads/2001/09/Borough-Market-street-food-market-london-nudge.jpg",
            "description": "Borough Market is a wholesale and retail food market in Southwark, London, England. It is one of the largest and oldest food markets in London, with a market on the site dating back to at least the 12th century.",
            "city": "london",
            "link": "https://wego.here.com/united-kingdom/london/mall/borough-market--826gcpvj-770480e9694e4cea87e7f4cdbcda1384?map=51.504925,-0.090344,15,normal&x=ep"
        },
        {
            "position": [
                51.50533,
                -0.116
            ],
            "title": "Royal Festival Hall",
            "imageUrl": "https://upload.wikimedia.org/wikipedia/commons/thumb/0/06/Royal_Festival_Hall_%2837366103611%29.jpg/800px-Royal_Festival_Hall_%2837366103611%29.jpg",
            "description": "The Royal Festival Hall is a 2,500-seat concert, dance and talks venue within Southbank Centre in London. It is situated on the South Bank of the River Thames, not far from Hungerford Bridge, in the London Borough of Lambeth.",
            "city": "london",
            "link": "https://wego.here.com/united-kingdom/london/theatre-music-culture/royal-festival-hall--826gcpvj-ecb8b7526637438ca3eea44e05dffc7c?map=51.50533,-0.116,15,normal&x=ep"
        },
        {
            "position": [
                51.51077,
                -0.13561
            ],
            "title": "Piccadilly Theatre",
            "imageUrl": "https://media-cdn.tripadvisor.com/media/photo-s/0d/54/46/52/auditorium-piccadilly.jpg",
            "description": "The Piccadilly Theatre is a West End theatre located at 16 Denman Street, behind Piccadilly Circus and adjacent to the Regent Palace Hotel, in the City of Westminster, England.",
            "city": "london",
            "link": "https://wego.here.com/united-kingdom/london/theatre-music-culture/piccadilly-theatre--826gcpvh-9deec40261a6475eb37998ef32cea428?map=51.51077,-0.13561,15,normal&x=ep"
        }
    ]